DESCRIPTION.txt
HexagonSC interrogator.bat
LICENSE.txt
README.txt
pyproject.toml
setup.cfg
setup.py
HexagonSC.egg-info/PKG-INFO
HexagonSC.egg-info/SOURCES.txt
HexagonSC.egg-info/dependency_links.txt
HexagonSC.egg-info/requires.txt
HexagonSC.egg-info/top_level.txt
Tesseract/ambiguous_words.1.html
Tesseract/ambiguous_words.exe
Tesseract/classifier_tester.1.html
Tesseract/classifier_tester.exe
Tesseract/cntraining.1.html
Tesseract/cntraining.exe
Tesseract/combine_lang_model.1.html
Tesseract/combine_lang_model.exe
Tesseract/combine_tessdata.1.html
Tesseract/combine_tessdata.exe
Tesseract/dawg2wordlist.1.html
Tesseract/dawg2wordlist.exe
Tesseract/iconv.dll
Tesseract/icudt64.dll
Tesseract/icuin64.dll
Tesseract/icuuc64.dll
Tesseract/libarchive-13.dll
Tesseract/libbz2-1.dll
Tesseract/libcairo-2.dll
Tesseract/libcurl-4.dll
Tesseract/libeay32.dll
Tesseract/libexpat-1.dll
Tesseract/libffi-6.dll
Tesseract/libfontconfig-1.dll
Tesseract/libfreetype-6.dll
Tesseract/libgcc_s_seh-1.dll
Tesseract/libgif-7.dll
Tesseract/libglib-2.0-0.dll
Tesseract/libgobject-2.0-0.dll
Tesseract/libgomp-1.dll
Tesseract/libharfbuzz-0.dll
Tesseract/libidn2-0.dll
Tesseract/libintl-8.dll
Tesseract/libjbig-2.dll
Tesseract/libjpeg-8.dll
Tesseract/liblept-5.dll
Tesseract/liblz4-1.dll
Tesseract/liblzma-5.dll
Tesseract/liblzo2-2.dll
Tesseract/libnettle-6.dll
Tesseract/libnghttp2-14.dll
Tesseract/libopenjp2.dll
Tesseract/libpango-1.0-0.dll
Tesseract/libpangocairo-1.0-0.dll
Tesseract/libpangoft2-1.0-0.dll
Tesseract/libpangowin32-1.0-0.dll
Tesseract/libpcre-1.dll
Tesseract/libpixman-1-0.dll
Tesseract/libpng16-16.dll
Tesseract/libssh2-1.dll
Tesseract/libstdc++-6.dll
Tesseract/libtesseract-5.dll
Tesseract/libtiff-5.dll
Tesseract/libunistring-2.dll
Tesseract/libwebp-7.dll
Tesseract/libwinpthread-1.dll
Tesseract/libxml2-2.dll
Tesseract/libzstd-1.dll
Tesseract/lstmeval.1.html
Tesseract/lstmeval.exe
Tesseract/lstmtraining.1.html
Tesseract/lstmtraining.exe
Tesseract/merge_unicharsets.1.html
Tesseract/merge_unicharsets.exe
Tesseract/mftraining.1.html
Tesseract/mftraining.exe
Tesseract/set_unicharset_properties.1.html
Tesseract/set_unicharset_properties.exe
HexagonSC-0.3.dist-info/LICENSE.txt
HexagonSC-0.3.dist-info/METADATA
HexagonSC-0.3.dist-info/WHEEL
HexagonSC-0.3.dist-info/top_level.txt
HexagonSC-0.3.dist-info/RECORD
