Metadata-Version: 2.1
Name: HexagonSC
Version: 0.3
Summary: Interrogates Bounties in SC from the contracts window
Home-page: https://github.com/
Author: TG
Author-email: Tg <tg3.383@gmail.com>
License: GNU public v3
Project-URL: Homepage, https://github.com/
Project-URL: Bug Tracker, https://github.com/
Keywords: Starcitizen,Bounty-hunting,bs4,
Classifier: Programming Language :: Python :: 3
Classifier: License :: OSI Approved :: GNU General Public License v3 (GPLv3)
Classifier: Operating System :: OS Independent
Requires-Python: >=3.7
License-File: LICENSE.txt
Requires-Dist: requests
Requires-Dist: tabulate
Requires-Dist: opencv-python
Requires-Dist: PIL
Requires-Dist: bs4
Requires-Dist: pytesseract
Requires-Dist: keyboard
